bench.py
ulhpc_ml_benchmark-0.0.2.dist-info/LICENSE
ulhpc_ml_benchmark-0.0.2.dist-info/METADATA
ulhpc_ml_benchmark-0.0.2.dist-info/WHEEL
ulhpc_ml_benchmark-0.0.2.dist-info/top_level.txt
ulhpc_ml_benchmark-0.0.2.dist-info/RECORD
