Metadata-Version: 2.1
Name: ulhpc_ml_benchmark
Version: 0.0.2
Summary: ML Benchmark used to compare CPUs
Author-email: Pierrick Pochelu <pierrick.pochelu@gmail.com>
Project-URL: Homepage, https://github.com/PierrickPochelu/ulhpc_ml_benchmark
Project-URL: Bug Tracker, https://github.com/PierrickPochelu/JaxDecompiler/issues
Classifier: Programming Language :: Python :: 3
Classifier: License :: OSI Approved :: GNU Lesser General Public License v3 (LGPLv3)
Classifier: Operating System :: OS Independent
Requires-Python: >=3.8
License-File: LICENSE
